djutils/__init__.py
djutils/admin.py
djutils/app_settings.py
djutils/asyncio.py
djutils/crypt.py
djutils/exceptions.py
djutils/http.py
djutils/ip.py
djutils/mail.py
djutils/mixins.py
djutils/models.py
djutils/number.py
djutils/transaction.py
djutils/db/__init__.py
djutils/db/extensions.py
djutils/db/functions.py
djutils/db/utils.py
djutils/db/backends/__init__.py
djutils/db/backends/cockroachdb/__init__.py
djutils/db/backends/cockroachdb/base.py
djutils/db/backends/postgresql/__init__.py
djutils/db/backends/postgresql/base.py
djutils-1.0.23.dist-info/LICENSE
djutils-1.0.23.dist-info/METADATA
djutils-1.0.23.dist-info/WHEEL
djutils-1.0.23.dist-info/top_level.txt
djutils-1.0.23.dist-info/RECORD
