Metadata-Version: 2.1
Name: djutils
Version: 1.0.23
Summary: Utilities for use with the django web framework
Home-page: https://github.com/Voltane-EU/djutils
Author: Manuel Stingl
Author-email: opensource@voltane.eu
License: GNU LGPLv2.1
Classifier: Programming Language :: Python :: 3
Classifier: Operating System :: OS Independent
Classifier: Framework :: Django
Classifier: Framework :: Django :: 2.0
Classifier: Framework :: Django :: 2.1
Classifier: Framework :: Django :: 2.2
Classifier: Framework :: Django :: 3.0
Classifier: Framework :: Django :: 3.1
Classifier: Framework :: Django :: 4.0
Requires-Python: >=3.6
License-File: LICENSE
Requires-Dist: django (>=2.0)
Requires-Dist: Pillow (>=6.0)
Requires-Dist: async-sync-tools
